stash_connection_lib/__init__.py
stash_connection_lib/core.py
stash_connection_lib-0.1.1.dist-info/METADATA
stash_connection_lib-0.1.1.dist-info/WHEEL
stash_connection_lib-0.1.1.dist-info/top_level.txt
stash_connection_lib-0.1.1.dist-info/RECORD
