Metadata-Version: 2.4
Name: stash-connection-lib
Version: 0.1.1
Summary: Beginner-friendly Stash GraphQL connection helpers for plugin developers
Author-email: Serechops <serechops@github.com>
License: MIT
Project-URL: Homepage, https://github.com/Serechops/Serechops-Stash
Project-URL: Repository, https://github.com/Serechops/Serechops-Stash/tree/main/stash-connection-lib
Project-URL: Bug Tracker, https://github.com/Serechops/Serechops-Stash/issues
Project-URL: Documentation, https://github.com/Serechops/Serechops-Stash/tree/main/stash-connection-lib#readme
Keywords: stash,graphql,plugin,helper,connection
Classifier: Development Status :: 4 - Beta
Classifier: Intended Audience :: Developers
Classifier: License :: OSI Approved :: MIT License
Classifier: Programming Language :: Python :: 3
Classifier: Programming Language :: Python :: 3.8
Classifier: Programming Language :: Python :: 3.9
Classifier: Programming Language :: Python :: 3.10
Classifier: Programming Language :: Python :: 3.11
Classifier: Programming Language :: Python :: 3.12
Classifier: Topic :: Software Development :: Libraries :: Python Modules
Classifier: Topic :: Internet :: WWW/HTTP :: Dynamic Content
Requires-Python: >=3.8
Requires-Dist: requests>=2.25.0
Provides-Extra: dev
Requires-Dist: pytest>=7.0.0; extra == "dev"
Requires-Dist: pytest-cov>=4.0.0; extra == "dev"
Requires-Dist: black>=22.0.0; extra == "dev"
Requires-Dist: flake8>=4.0.0; extra == "dev"
Requires-Dist: mypy>=0.950; extra == "dev"
